src/commands/init.py
src/core/settings.py
src/main.py
src/ui/header.py
src/ui/icons.py
quicky_repo-1.0.0.dist-info/METADATA
quicky_repo-1.0.0.dist-info/WHEEL
quicky_repo-1.0.0.dist-info/LICENSE
quicky_repo-1.0.0.dist-info/RECORD
