Metadata-Version: 2.1
Name: quicky-repo
Version: 1.0.0
Summary: ⚡ Initialize your projects as fast as you want.
License: GPL-v3
Author: Kauê Fraga Rodrigues
Author-email: kauefragarodrigues456@gmail.com
Requires-Python: >=3.8,<4.0
Classifier: License :: Other/Proprietary License
Classifier: Programming Language :: Python :: 3
Classifier: Programming Language :: Python :: 3.8
Classifier: Programming Language :: Python :: 3.9
Classifier: Programming Language :: Python :: 3.10
Classifier: Programming Language :: Python :: 3.11
Requires-Dist: click (>=8.1.3,<9.0.0)
Requires-Dist: pyfiglet (>=0.8.post1,<0.9)
Requires-Dist: rich (>=13.3.1,<14.0.0)
